<?xml version="1.0" encoding="UTF-8"?>
<!DOCTYPE mapper PUBLIC "-//mybatis.org//DTD Mapper 3.0//EN" "http://mybatis.org/dtd/mybatis-3-mapper.dtd">
<mapper namespace="com.echoamoy.holdlens.server.infrastructure.dao.IFundTopHoldingDao">

    <resultMap id="BaseResultMap" type="com.echoamoy.holdlens.server.infrastructure.dao.po.FundTopHoldingPO">
        <id column="id" property="id"/>
        <result column="fund_code" property="fundCode"/>
        <result column="rank_no" property="rankNo"/>
        <result column="stock_name" property="stockName"/>
        <result column="stock_code" property="stockCode"/>
        <result column="market" property="market"/>
        <result column="holding_ratio" property="holdingRatio"/>
        <result column="quarter_change_type" property="quarterChangeType"/>
        <result column="quarter_change_value" property="quarterChangeValue"/>
        <result column="create_time" property="createTime"/>
        <result column="update_time" property="updateTime"/>
    </resultMap>

    <sql id="Base_Column_List">
        id, fund_code, rank_no, stock_name, stock_code, market,
        holding_ratio, quarter_change_type, quarter_change_value, create_time, update_time
    </sql>

    <insert id="insert" parameterType="com.echoamoy.holdlens.server.infrastructure.dao.po.FundTopHoldingPO" useGeneratedKeys="true" keyProperty="id">
        INSERT INTO fund_top_holding (
            fund_code, rank_no, stock_name, stock_code, market,
            holding_ratio, quarter_change_type, quarter_change_value
        ) VALUES (
            #{fundCode}, #{rankNo}, #{stockName}, #{stockCode}, #{market},
            #{holdingRatio}, #{quarterChangeType}, #{quarterChangeValue}
        )
    </insert>

    <update id="update" parameterType="com.echoamoy.holdlens.server.infrastructure.dao.po.FundTopHoldingPO">
        UPDATE fund_top_holding
        SET stock_name = #{stockName},
            stock_code = #{stockCode},
            market = #{market},
            holding_ratio = #{holdingRatio},
            quarter_change_type = #{quarterChangeType},
            quarter_change_value = #{quarterChangeValue},
            update_time = CURRENT_TIMESTAMP
        WHERE id = #{id}
    </update>

    <delete id="deleteByFundCode">
        DELETE FROM fund_top_holding
        WHERE fund_code = #{fundCode}
    </delete>

    <delete id="deleteByIds">
        DELETE FROM fund_top_holding
        WHERE id IN
        <foreach collection="ids" item="id" open="(" separator="," close=")">
            #{id}
        </foreach>
    </delete>

    <select id="selectById" resultMap="BaseResultMap">
        SELECT <include refid="Base_Column_List"/>
        FROM fund_top_holding
        WHERE id = #{id}
    </select>

    <select id="selectByFundCodes" resultMap="BaseResultMap">
        SELECT <include refid="Base_Column_List"/>
        FROM fund_top_holding
        WHERE fund_code IN
        <foreach collection="fundCodes" item="fundCode" open="(" separator="," close=")">
            #{fundCode}
        </foreach>
        ORDER BY fund_code ASC, rank_no ASC
    </select>

    <select id="selectByStockCode" resultMap="BaseResultMap">
        SELECT <include refid="Base_Column_List"/>
        FROM fund_top_holding
        WHERE stock_code = #{stockCode}
        ORDER BY id DESC
    </select>

</mapper>
